[
    {
		"id": 0,
        "scientificName": "Proceratophrys goyana", 
		"vernacularName": "Sapo-de-chifre",
		"family": "Odontophrynidae",
        "slug": "proceratophrys-goyana", 
        "profilePhoto": "", 
        "scientificNameAuthorship": "", 
        "size": 1,
		"occurrenceStates":["DF", "GO"],
		"description": "some"
    }, 

    {
		"id": 1,
		"scientificName": "Ameerega flavopicta", 
		"vernacularName": "Sapo-flecha",
		"family": "Dendrobatidae",
        "slug": "ameerega-flavopicta", 
        "profilePhoto": "", 
        "scientificNameAuthorship": "", 
        "size": "some",
		"occurrenceStates":["DF", "GO"],
		"description": "some"
    }
 ]